prismatique/__init__.py
prismatique/_signal.py
prismatique/aperture.py
prismatique/cbed.py
prismatique/discretization.py
prismatique/load.py
prismatique/sample.py
prismatique/thermal.py
prismatique/tilt.py
prismatique/version.py
prismatique/hrtem/__init__.py
prismatique/hrtem/image.py
prismatique/hrtem/output.py
prismatique/hrtem/sim.py
prismatique/hrtem/system.py
prismatique/scan/__init__.py
prismatique/scan/rectangular.py
prismatique/stem/__init__.py
prismatique/stem/sim.py
prismatique/stem/system.py
prismatique/stem/output/__init__.py
prismatique/stem/output/base.py
prismatique/stem/output/multislice.py
prismatique/stem/output/prism.py
prismatique/worker/__init__.py
prismatique/worker/cpu.py
prismatique/worker/gpu.py
prismatique-0.0.4.dist-info/licenses/LICENSE
prismatique-0.0.4.dist-info/METADATA
prismatique-0.0.4.dist-info/WHEEL
prismatique-0.0.4.dist-info/top_level.txt
prismatique-0.0.4.dist-info/RECORD
