Metadata-Version: 2.4
Name: prismatique
Version: 0.0.4
Summary: A wrapper to the Python library `pyprismatic`, which is a library for simulating CBED, STEM, and HRTEM experiments using Multislice algorithms.
Author-email: Matthew Fitzpatrick <matthew.rc.fitzpatrick@gmail.com>
Project-URL: Homepage, https://mrfitzpa.github.io/prismatique
Project-URL: Repository, https://github.com/mrfitzpa/prismatique
Keywords: hyperspy,multislice,CBED,STEM,HRTEM,GPU,prismatic,pyprismatic,microscopy,electron beam,electron probe
Classifier: License :: OSI Approved :: GNU General Public License v3 (GPLv3)
Classifier: Development Status :: 5 - Production/Stable
Classifier: Intended Audience :: Science/Research
Classifier: Programming Language :: Python
Classifier: Programming Language :: Python :: 3
Classifier: Programming Language :: Python :: 3.9
Classifier: Programming Language :: Python :: 3.10
Classifier: Programming Language :: Python :: 3.11
Classifier: Programming Language :: Python :: 3.12
Classifier: Operating System :: OS Independent
Classifier: Natural Language :: English
Requires-Python: >=3.9
License-File: LICENSE
Requires-Dist: embeam>=0.0.5
Requires-Dist: h5pywrappers
Requires-Dist: hyperspy_gui_ipywidgets
Provides-Extra: tests
Requires-Dist: pytest-cov; extra == "tests"
Provides-Extra: examples
Requires-Dist: jupyter; extra == "examples"
Requires-Dist: ipympl; extra == "examples"
Provides-Extra: docs
Requires-Dist: sphinx<7; extra == "docs"
Requires-Dist: sphinx_rtd_theme; extra == "docs"
Requires-Dist: sphinx-autodoc-typehints; extra == "docs"
Requires-Dist: numpydoc; extra == "docs"
Requires-Dist: docutils; extra == "docs"
Provides-Extra: all
Requires-Dist: prismatique[docs,examples,tests]; extra == "all"
Dynamic: license-file
